dwave/optimization/states.cpython-311-darwin.so
dwave/optimization/_utilities.pxd
dwave/optimization/states.pyx
dwave/optimization/_model.pyi
dwave/optimization/__init__.pxd
dwave/optimization/_model.pxd
dwave/optimization/__init__.py
dwave/optimization/model.py
dwave/optimization/generators.py
dwave/optimization/states.pyi
dwave/optimization/_model.cpython-311-darwin.so
dwave/optimization/libdwave-optimization.dylib
dwave/optimization/_model.pyx
dwave/optimization/_utilities.cpython-311-darwin.so
dwave/optimization/model.pxd
dwave/optimization/py.typed
dwave/optimization/utilities.py
dwave/optimization/mathematical.py
dwave/optimization/expression.py
dwave/optimization/states.pxd
dwave/optimization/_utilities.pyx
dwave/optimization/include/dwave-optimization/typing.hpp
dwave/optimization/include/dwave-optimization/array.hpp
dwave/optimization/include/dwave-optimization/iterators.hpp
dwave/optimization/include/dwave-optimization/functional.hpp
dwave/optimization/include/dwave-optimization/graph.hpp
dwave/optimization/include/dwave-optimization/type_list.hpp
dwave/optimization/include/dwave-optimization/state.hpp
dwave/optimization/include/dwave-optimization/common.hpp
dwave/optimization/include/dwave-optimization/fraction.hpp
dwave/optimization/include/dwave-optimization/nodes.hpp
dwave/optimization/include/dwave-optimization/nodes/testing.hpp
dwave/optimization/include/dwave-optimization/nodes/reduce.hpp
dwave/optimization/include/dwave-optimization/nodes/binaryop.hpp
dwave/optimization/include/dwave-optimization/nodes/unaryop.hpp
dwave/optimization/include/dwave-optimization/nodes/quadratic_model.hpp
dwave/optimization/include/dwave-optimization/nodes/set_routines.hpp
dwave/optimization/include/dwave-optimization/nodes/lp.hpp
dwave/optimization/include/dwave-optimization/nodes/inputs.hpp
dwave/optimization/include/dwave-optimization/nodes/sorting.hpp
dwave/optimization/include/dwave-optimization/nodes/interpolation.hpp
dwave_optimization-0.6.10.dist-info/RECORD
dwave_optimization-0.6.10.dist-info/LICENSE
dwave_optimization-0.6.10.dist-info/WHEEL
dwave_optimization-0.6.10.dist-info/METADATA
