Metadata-Version: 2.1
Name: dwave-optimization
Version: 0.6.10
Summary: Enables the formulation of nonlinear models for industrial optimization problems.
Author-Email: "D-Wave Inc." <tools@dwavesys.com>
License:                                  Apache License
Classifier: License :: OSI Approved :: Apache Software License
Classifier: Operating System :: Microsoft :: Windows
Classifier: Operating System :: POSIX
Classifier: Operating System :: Unix
Classifier: Operating System :: MacOS
Classifier: Programming Language :: Python
Classifier: Programming Language :: Python :: 3
Classifier: Programming Language :: Python :: 3.10
Classifier: Programming Language :: Python :: 3.11
Classifier: Programming Language :: Python :: 3.12
Classifier: Programming Language :: Python :: 3.13
Classifier: Programming Language :: Python :: 3.14
Classifier: Programming Language :: Python :: 3 :: Only
Classifier: Programming Language :: Python :: Implementation :: CPython
Project-URL: Changelog, https://github.com/dwavesystems/dwave-optimization/releases
Project-URL: Documentation, https://docs.dwavequantum.com
Project-URL: Source Code, https://github.com/dwavesystems/dwave-optimization
Requires-Python: >=3.10
Requires-Dist: numpy>=1.21.3
